hasty_helix/__init__.py
hasty_helix/analyzer.py
hasty_helix/cli.py
hasty_helix-0.3.0.dist-info/METADATA
hasty_helix-0.3.0.dist-info/WHEEL
hasty_helix-0.3.0.dist-info/entry_points.txt
hasty_helix-0.3.0.dist-info/top_level.txt
hasty_helix-0.3.0.dist-info/RECORD
