Metadata-Version: 2.1
Name: hasty-helix
Version: 0.3.0
Summary: A package to analyze transactions from a CSV file.
Author: Semyon Drozdov
Author-email: Semyon Drozdov <s.drozdov@edu.centraluniversity.ru>
License: MIT
Requires-Python: >=3.8
Requires-Dist: pandas
